demo/video_detection.py
pyl/__init__.py
pyl/_legacy/Compiler.py
pyl/_legacy/Datapoint.py
pyl/_legacy/Models.py
pyl/_legacy/Utils.py
pyl/_legacy/configs/__init__.py
pyl/_legacy/guis/AugmentationsGUI.py
pyl/_legacy/guis/__init__.py
pyl/data/__init__.py
pyl/data/augmentation.py
pyl/data/reduction.py
pyl/data/utils.py
pyl/models/__init__.py
pyl/models/CNN/__init__.py
pyl/models/CNN/src/CNN.py
pyl/models/CNN/src/CNNClassificationResNet.py
pyl/models/CNN/src/CNNDetectionFasterRCNN.py
pyl/models/CNN/src/CNNDetectionRetinaNet.py
pyl/models/CNN/src/CNNDetectionSSD.py
pyl/models/CNN/src/CNNKeypoint.py
pyl/models/CNN/src/CNNSegmentationDeeplabV3.py
pyl/models/CNN/src/CNNSegmentationFCN.py
pyl/models/CNN/src/datasets/__init__.py
pyl/models/CNN/src/datasets/deeplabdataset.py
pyl/models/CNN/src/datasets/fasterrcnndataset.py
pyl/models/CNN/src/datasets/fcndataset.py
pyl/models/CNN/src/datasets/resnetdataset.py
pyl/models/CNN/src/datasets/ssddataset.py
pyl/models/CNN/src/losses/ssdloss.py
pyl/models/CNN/src/processing/__init__.py
pyl/models/CNN/src/processing/datacompose.py
pyl/models/CNN/src/processing/datatransforms.py
pyl/models/CNN/src/processing/targetcompose.py
pyl/models/CNN/src/processing/targettransforms.py
pyl/models/CNN/src/samplers/basesampler.py
pyl/models/CNN/src/samplers/sampler.py
pyl/models/CNN/src/samplers/singleclssampler.py
pyl/models/LLM/__init__.py
pyl/models/LLM/src/LLM.py
pyl/models/LLM/src/LLMDecodingMistral7b.py
pyl/models/LLM/src/LLMDecodingOPT125m.py
pyl/models/LLM/src/LLMDecodingPhi.py
pyl/models/LLM/src/LLMDecodingPhiMoE.py
pyl/models/LLM/src/LLMEncodingBARTLargeMNLI.py
pyl/models/LLM/src/LLMEncodingDeBERTaV3Base.py
pyl/models/LLM/src/LLMEncodingDeBERTaV3BaseMNLI.py
pyl/models/LLM/src/LLMEncodingDeBERTaV3Large.py
pyl/utils/__init__.py
pyl/utils/compiler.py
pyl/utils/labeller.py
pyl/utils/utils.py
test/import_test.py
test/main.py
PyYel-0.1.0.dist-info/METADATA
PyYel-0.1.0.dist-info/WHEEL
PyYel-0.1.0.dist-info/top_level.txt
PyYel-0.1.0.dist-info/RECORD
