Metadata-Version: 2.1
Name: PyYel
Version: 0.1.0
Summary: Transformers release
Home-page: https://github.com/Nayel-Blidi/PyYel
Author: Nayel Maxime BLIDI
Author-email: Nayel BLIDI <nayel.blidi@gmail.com>
Classifier: Programming Language :: Python :: 3
Classifier: License :: OSI Approved :: MIT License
Classifier: Operating System :: OS Independent
Requires-Python: >=3.6
Requires-Dist: numpy<2
Requires-Dist: pandas
Requires-Dist: opencv-python
Requires-Dist: python-dotenv==1.0.1
Requires-Dist: tqdm
Requires-Dist: scikit-learn
Requires-Dist: matplotlib
Requires-Dist: transformers
Requires-Dist: torch==2.4.1
Requires-Dist: torchvision
Requires-Dist: datasets
Requires-Dist: accelerate
Requires-Dist: protobuf==5.28.2
Requires-Dist: sentencepiece==0.2.0
